LICENSE
README.md
setup.py
canopto/__init__.py
canopto/__main__.py
canopto.egg-info/PKG-INFO
canopto.egg-info/SOURCES.txt
canopto.egg-info/dependency_links.txt
canopto.egg-info/entry_points.txt
canopto.egg-info/not-zip-safe
canopto.egg-info/requires.txt
canopto.egg-info/top_level.txt
canopto/classes/__init__.py
canopto/classes/course.py
canopto/classes/courses.py
canopto/classes/file.py
canopto/classes/folder.py
canopto/classes/menuoption.py
canopto/core/__init__.py
canopto/core/authenticate.py
canopto/core/config.py
canopto/core/menu.py
canopto/core/web.py
canopto/ui/__init__.py
canopto/ui/messages.py
canopto/ui/tui.py